{
    "siteCount": 49290,
    "recentlyMoved": [
        {
            "domain_name": "noblementors.com",
            "destination": "SiteGround",
            "date": "2025-02-27 14:41:21"
        },
        {
            "domain_name": "uptowncosmeticimplantdentistry.com",
            "destination": "Hostinger",
            "date": "2025-02-27 14:39:55"
        },
        {
            "domain_name": "nabie.org",
            "destination": "GoDaddy",
            "date": "2025-02-27 14:29:55"
        },
        {
            "domain_name": "www.veteransleadershipprogram.org",
            "destination": "Pressable",
            "date": "2025-02-27 14:22:01"
        },
        {
            "domain_name": "dmvhousehunt.com",
            "destination": "GoDaddy",
            "date": "2025-02-27 14:13:09"
        },
        {
            "domain_name": "mdsbuilders.com",
            "destination": "Digital Ocean",
            "date": "2025-02-27 14:05:04"
        },
        {
            "domain_name": "emeraldrealtyil.com",
            "destination": "Wordify",
            "date": "2025-02-27 13:52:20"
        },
        {
            "domain_name": "emeraldpropertymgt.com",
            "destination": "Wordify",
            "date": "2025-02-27 13:52:20"
        },
        {
            "domain_name": "stonenaturalresources.com",
            "destination": "Pressable",
            "date": "2025-02-27 13:51:17"
        },
        {
            "domain_name": "lakeparkseniorliving.com",
            "destination": "SiteGround",
            "date": "2025-02-27 13:43:47"
        },
        {
            "domain_name": "www.simi4smiles.com",
            "destination": "Kinsta",
            "date": "2025-02-27 13:40:38"
        },
        {
            "domain_name": "teacherassist.co.uk",
            "destination": "SiteGround",
            "date": "2025-02-27 13:39:42"
        },
        {
            "domain_name": "www.newbernac.com",
            "destination": "Digital Ocean",
            "date": "2025-02-27 13:31:27"
        },
        {
            "domain_name": "mattressfoundations.com",
            "destination": "SiteGround",
            "date": "2025-02-27 13:31:01"
        },
        {
            "domain_name": "skriftlig.no",
            "destination": "Digital Ocean",
            "date": "2025-02-27 13:28:35"
        },
        {
            "domain_name": "www.westerlygroup.com",
            "destination": "Hostinger",
            "date": "2025-02-27 13:28:28"
        },
        {
            "domain_name": "www.lydiajsartain.com",
            "destination": "Pressable",
            "date": "2025-02-27 13:25:56"
        },
        {
            "domain_name": "statelinecleaners.com",
            "destination": "Wordify",
            "date": "2025-02-27 13:23:59"
        },
        {
            "domain_name": "www.pilchuckvillage.com",
            "destination": "Hostinger",
            "date": "2025-02-27 13:05:46"
        },
        {
            "domain_name": "www.hestandhomeinspections.com",
            "destination": "Pressable",
            "date": "2025-02-27 13:00:39"
        },
        {
            "domain_name": "www.portofilwaco.com",
            "destination": "Digital Ocean",
            "date": "2025-02-27 12:55:44"
        },
        {
            "domain_name": "bonzerchemicalsupplies.com.au",
            "destination": "SiteGround",
            "date": "2025-02-27 12:46:40"
        },
        {
            "domain_name": "assuranceroofingonline.com",
            "destination": "GoDaddy",
            "date": "2025-02-27 12:33:01"
        },
        {
            "domain_name": "rhymeandreason.net",
            "destination": "SiteGround",
            "date": "2025-02-27 12:21:30"
        },
        {
            "domain_name": "broadwaytreatmentcenter.com",
            "destination": "SiteGround",
            "date": "2025-02-27 12:20:35"
        },
        {
            "domain_name": "www.furnaceexchange.com",
            "destination": "Namecheap",
            "date": "2025-02-27 12:10:20"
        },
        {
            "domain_name": "www.blackdiamondclaimssolutions.com",
            "destination": "Hostinger",
            "date": "2025-02-27 12:09:58"
        },
        {
            "domain_name": "www.completersinc.com",
            "destination": "Digital Ocean",
            "date": "2025-02-27 12:04:25"
        },
        {
            "domain_name": "www.a-allcomfort.com",
            "destination": "Digital Ocean",
            "date": "2025-02-27 11:44:46"
        },
        {
            "domain_name": "oakbrooklasik.com",
            "destination": "Hostinger",
            "date": "2025-02-27 11:19:41"
        },
        {
            "domain_name": "nationalstemcelltherapy.com",
            "destination": "InMotion Hosting",
            "date": "2025-02-27 10:42:28"
        },
        {
            "domain_name": "familyeyephysicians.com",
            "destination": "Hostinger",
            "date": "2025-02-27 10:25:25"
        },
        {
            "domain_name": "medicaloi.com",
            "destination": "OVH",
            "date": "2025-02-27 10:22:35"
        },
        {
            "domain_name": "martindawesrentals.com",
            "destination": "Kinsta",
            "date": "2025-02-27 10:21:29"
        },
        {
            "domain_name": "useful-structures.com",
            "destination": "Kinsta",
            "date": "2025-02-27 10:15:14"
        },
        {
            "domain_name": "www.oiltanksplus.co.uk",
            "destination": "Hostinger",
            "date": "2025-02-27 09:44:11"
        },
        {
            "domain_name": "lakesideresidentialpark.co.uk",
            "destination": "Digital Ocean",
            "date": "2025-02-27 09:09:38"
        },
        {
            "domain_name": "square-1balustrades.co.uk",
            "destination": "Kinsta",
            "date": "2025-02-27 09:07:18"
        },
        {
            "domain_name": "intergeneration.ch",
            "destination": "Kinsta",
            "date": "2025-02-27 09:03:43"
        },
        {
            "domain_name": "www.dsagolf.co.uk",
            "destination": "SiteGround",
            "date": "2025-02-27 08:52:52"
        },
        {
            "domain_name": "johnlukechica.com",
            "destination": "Bluehost",
            "date": "2025-02-27 08:34:17"
        },
        {
            "domain_name": "gpo.co.nz",
            "destination": "Digital Ocean",
            "date": "2025-02-27 08:28:42"
        },
        {
            "domain_name": "patriciaaraque.com",
            "destination": "Namecheap",
            "date": "2025-02-27 07:49:12"
        },
        {
            "domain_name": "akgcreative.com",
            "destination": "Pressable",
            "date": "2025-02-27 07:43:47"
        },
        {
            "domain_name": "www.insidecasinovietnam.com",
            "destination": "Kinsta",
            "date": "2025-02-27 07:38:35"
        },
        {
            "domain_name": "www.insidecasinothailand.com",
            "destination": "Kinsta",
            "date": "2025-02-27 07:38:35"
        },
        {
            "domain_name": "www.insidecasinomalaysia.com",
            "destination": "Kinsta",
            "date": "2025-02-27 07:38:35"
        },
        {
            "domain_name": "www.insidecasinokorea.com",
            "destination": "Kinsta",
            "date": "2025-02-27 07:38:35"
        },
        {
            "domain_name": "www.insidecasinoindonesia.com",
            "destination": "Kinsta",
            "date": "2025-02-27 07:38:35"
        },
        {
            "domain_name": "www.insidecasino.jp",
            "destination": "Kinsta",
            "date": "2025-02-27 07:38:35"
        },
        {
            "domain_name": "theperformanceranch.com",
            "destination": "Digital Ocean",
            "date": "2025-02-27 06:02:03"
        },
        {
            "domain_name": "crossfitteneo.com",
            "destination": "Digital Ocean",
            "date": "2025-02-27 05:49:25"
        },
        {
            "domain_name": "crossfitgeelong.com.au",
            "destination": "Digital Ocean",
            "date": "2025-02-27 05:49:25"
        },
        {
            "domain_name": "www.superyachtsociety.org",
            "destination": "Digital Ocean",
            "date": "2025-02-27 05:38:02"
        },
        {
            "domain_name": "brandonberlew.com",
            "destination": "Namecheap",
            "date": "2025-02-27 04:51:54"
        },
        {
            "domain_name": "hyrebar.com",
            "destination": "Pressable",
            "date": "2025-02-27 04:32:23"
        },
        {
            "domain_name": "blog.blablacar.fr",
            "destination": "Pressable",
            "date": "2025-02-27 04:31:18"
        },
        {
            "domain_name": "azpoolkeeper.com",
            "destination": "SiteGround",
            "date": "2025-02-27 04:24:50"
        },
        {
            "domain_name": "arizonaasda.org",
            "destination": "SiteGround",
            "date": "2025-02-27 04:24:22"
        },
        {
            "domain_name": "arrowhomecare.net",
            "destination": "SiteGround",
            "date": "2025-02-27 04:06:07"
        },
        {
            "domain_name": "forkinpepe.com",
            "destination": "Pressable",
            "date": "2025-02-27 03:31:23"
        },
        {
            "domain_name": "3qfitness.com",
            "destination": "Digital Ocean",
            "date": "2025-02-27 03:08:38"
        },
        {
            "domain_name": "eternityandtaxes.com",
            "destination": "Pressable",
            "date": "2025-02-27 02:28:22"
        },
        {
            "domain_name": "allsystemsgone.com",
            "destination": "Pressable",
            "date": "2025-02-27 02:27:49"
        },
        {
            "domain_name": "zellifestylecollective.com",
            "destination": "Namecheap",
            "date": "2025-02-27 02:27:39"
        },
        {
            "domain_name": "mountviewbf.org",
            "destination": "SiteGround",
            "date": "2025-02-27 02:07:19"
        },
        {
            "domain_name": "www.spencerfane.com",
            "destination": "Kinsta",
            "date": "2025-02-27 01:53:32"
        },
        {
            "domain_name": "tobeme.com.au",
            "destination": "Kinsta",
            "date": "2025-02-27 01:43:51"
        },
        {
            "domain_name": "minesource.com",
            "destination": "GoDaddy",
            "date": "2025-02-27 01:43:47"
        },
        {
            "domain_name": "www.newclairvauxvineyard.com",
            "destination": "SiteGround",
            "date": "2025-02-27 01:35:58"
        },
        {
            "domain_name": "liveoakwf.com",
            "destination": "SiteGround",
            "date": "2025-02-27 01:23:44"
        },
        {
            "domain_name": "hiltonhomes.ca",
            "destination": "Pressable",
            "date": "2025-02-27 00:52:26"
        },
        {
            "domain_name": "www.dwilawyerstexas.com",
            "destination": "Digital Ocean",
            "date": "2025-02-27 00:47:32"
        },
        {
            "domain_name": "www.dvcresaleexperts.com",
            "destination": "SiteGround",
            "date": "2025-02-27 00:47:32"
        },
        {
            "domain_name": "califormulated.com",
            "destination": "Pressable",
            "date": "2025-02-27 00:44:46"
        },
        {
            "domain_name": "harristyres.co.nz",
            "destination": "Digital Ocean",
            "date": "2025-02-27 00:39:50"
        },
        {
            "domain_name": "alisonkriel.com",
            "destination": "WordPress.com",
            "date": "2025-02-27 00:20:57"
        },
        {
            "domain_name": "heavenlysoulandspirit.com",
            "destination": "Liquid Web",
            "date": "2025-02-27 00:04:26"
        },
        {
            "domain_name": "www.counciloakperio.com",
            "destination": "Kinsta",
            "date": "2025-02-27 00:01:17"
        },
        {
            "domain_name": "grosslawllc.com",
            "destination": "Kinsta",
            "date": "2025-02-26 23:44:19"
        },
        {
            "domain_name": "twoadventuroussouls.com",
            "destination": "Digital Ocean",
            "date": "2025-02-26 22:41:48"
        },
        {
            "domain_name": "www.wingsinsurance.com",
            "destination": "Digital Ocean",
            "date": "2025-02-26 22:20:52"
        },
        {
            "domain_name": "mahaiwe.org",
            "destination": "Pressable",
            "date": "2025-02-26 22:07:47"
        },
        {
            "domain_name": "lclspas.com",
            "destination": "Pressable",
            "date": "2025-02-26 21:49:28"
        },
        {
            "domain_name": "www.physicianseyecare.com",
            "destination": "Kinsta",
            "date": "2025-02-26 21:15:54"
        },
        {
            "domain_name": "johanneandamanda.com",
            "destination": "SiteGround",
            "date": "2025-02-26 21:14:45"
        },
        {
            "domain_name": "www.sportcourtnortherncalifornia.com",
            "destination": "Digital Ocean",
            "date": "2025-02-26 21:10:22"
        },
        {
            "domain_name": "lonestarpromoving.com",
            "destination": "SiteGround",
            "date": "2025-02-26 21:10:22"
        },
        {
            "domain_name": "jcraigmorrisonmd.com",
            "destination": "Kinsta",
            "date": "2025-02-26 20:54:49"
        },
        {
            "domain_name": "bobblake.ca",
            "destination": "SiteGround",
            "date": "2025-02-26 20:53:21"
        },
        {
            "domain_name": "instep-podiatry.com",
            "destination": "Kinsta",
            "date": "2025-02-26 20:39:21"
        },
        {
            "domain_name": "instantfreightsolutions.com",
            "destination": "GoDaddy",
            "date": "2025-02-26 20:39:21"
        },
        {
            "domain_name": "innovatealbion.org",
            "destination": "Namecheap",
            "date": "2025-02-26 20:31:57"
        },
        {
            "domain_name": "www.kimberleygohmd.com",
            "destination": "Kinsta",
            "date": "2025-02-26 20:31:18"
        },
        {
            "domain_name": "beltoneg4.com",
            "destination": "Digital Ocean",
            "date": "2025-02-26 20:28:30"
        },
        {
            "domain_name": "www.boccebuildersofamerica.com",
            "destination": "Digital Ocean",
            "date": "2025-02-26 20:22:37"
        },
        {
            "domain_name": "rarediseases.org",
            "destination": "SiteGround",
            "date": "2025-02-26 20:17:31"
        },
        {
            "domain_name": "www.cushioncourts.com",
            "destination": "Digital Ocean",
            "date": "2025-02-26 20:04:11"
        },
        {
            "domain_name": "bensducts.com",
            "destination": "Digital Ocean",
            "date": "2025-02-26 20:00:31"
        },
        {
            "domain_name": "aylmerfamilydental.com",
            "destination": "Digital Ocean",
            "date": "2025-02-26 19:57:01"
        }
    ],
    "dailyMovedStat": {
        "2024-09-21": "94",
        "2024-09-22": "199",
        "2024-09-23": "345",
        "2024-09-24": "492",
        "2024-09-25": "709",
        "2024-09-26": "920",
        "2024-09-27": "1151",
        "2024-09-28": "1378",
        "2024-09-29": "1581",
        "2024-09-30": "1808",
        "2024-10-01": "2030",
        "2024-10-02": "2247",
        "2024-10-03": "2544",
        "2024-10-04": "2807",
        "2024-10-05": "3040",
        "2024-10-06": "3176",
        "2024-10-07": "3225",
        "2024-10-08": "3236",
        "2024-10-09": "5144",
        "2024-10-10": "5833",
        "2024-10-11": "5893",
        "2024-10-12": "5998",
        "2024-10-13": "6306",
        "2024-10-14": "6505",
        "2024-10-15": "6891",
        "2024-10-16": "7295",
        "2024-10-17": "7706",
        "2024-10-18": "8159",
        "2024-10-19": "8726",
        "2024-10-20": "8887",
        "2024-10-21": "9024",
        "2024-10-22": "9363",
        "2024-10-23": "9983",
        "2024-10-24": "10540",
        "2024-10-25": "11045",
        "2024-10-26": "11549",
        "2024-10-27": "11717",
        "2024-10-28": "11903",
        "2024-10-29": "12374",
        "2024-10-30": "12971",
        "2024-10-31": "13468",
        "2024-11-01": "13969",
        "2024-11-02": "14516",
        "2024-11-03": "14627",
        "2024-11-04": "14709",
        "2024-11-05": "15080",
        "2024-11-06": "16045",
        "2024-11-07": "16446",
        "2024-11-08": "16798",
        "2024-11-09": "17121",
        "2024-11-10": "17418",
        "2024-11-11": "17860",
        "2024-11-12": "18294",
        "2024-11-13": "18512",
        "2024-11-14": "18951",
        "2024-11-15": "19435",
        "2024-11-16": "19838",
        "2024-11-17": "19924",
        "2024-11-18": "20048",
        "2024-11-19": "20351",
        "2024-11-20": "20977",
        "2024-11-21": "21733",
        "2024-11-22": "22351",
        "2024-11-23": "22794",
        "2024-11-24": "22890",
        "2024-11-25": "23102",
        "2024-11-26": "23520",
        "2024-11-27": "23890",
        "2024-11-28": "24253",
        "2024-11-29": "24507",
        "2024-11-30": "24714",
        "2024-12-01": "24827",
        "2024-12-02": "24959",
        "2024-12-03": "25264",
        "2024-12-04": "25595",
        "2024-12-05": "25980",
        "2024-12-06": "26353",
        "2024-12-07": "26706",
        "2024-12-08": "26828",
        "2024-12-09": "26944",
        "2024-12-10": "27235",
        "2024-12-11": "27669",
        "2024-12-12": "28038",
        "2024-12-13": "28452",
        "2024-12-14": "28737",
        "2024-12-15": "28865",
        "2024-12-16": "28997",
        "2024-12-17": "29355",
        "2024-12-18": "29794",
        "2024-12-19": "30255",
        "2024-12-20": "30754",
        "2024-12-21": "31178",
        "2024-12-22": "31290",
        "2024-12-23": "31427",
        "2024-12-24": "31729",
        "2024-12-25": "31943",
        "2024-12-26": "32052",
        "2024-12-27": "32242",
        "2024-12-28": "32470",
        "2024-12-29": "32577",
        "2024-12-30": "32689",
        "2024-12-31": "32943",
        "2025-01-01": "33166",
        "2025-01-02": "33269",
        "2025-01-03": "33531",
        "2025-01-04": "33774",
        "2025-01-05": "33872",
        "2025-01-06": "33979",
        "2025-01-07": "34265",
        "2025-01-08": "34535",
        "2025-01-09": "34828",
        "2025-01-10": "35162",
        "2025-01-11": "35441",
        "2025-01-12": "35553",
        "2025-01-13": "35677",
        "2025-01-14": "35976",
        "2025-01-15": "36380",
        "2025-01-16": "36807",
        "2025-01-17": "37213",
        "2025-01-18": "37540",
        "2025-01-19": "37667",
        "2025-01-20": "38458",
        "2025-01-21": "38845",
        "2025-01-22": "39215",
        "2025-01-23": "39518",
        "2025-01-24": "39857",
        "2025-01-25": "40177",
        "2025-01-26": "40289",
        "2025-01-27": "40428",
        "2025-01-28": "40722",
        "2025-01-29": "41070",
        "2025-01-30": "41418",
        "2025-01-31": "41869",
        "2025-02-01": "42225",
        "2025-02-02": "42375",
        "2025-02-03": "42514",
        "2025-02-04": "42959",
        "2025-02-05": "43342",
        "2025-02-06": "43666",
        "2025-02-07": "44032",
        "2025-02-08": "44336",
        "2025-02-09": "44458",
        "2025-02-10": "44604",
        "2025-02-11": "44944",
        "2025-02-12": "45348",
        "2025-02-13": "45683",
        "2025-02-14": "46049",
        "2025-02-15": "46347",
        "2025-02-16": "46459",
        "2025-02-17": "46601",
        "2025-02-18": "46847",
        "2025-02-19": "47142",
        "2025-02-20": "47482",
        "2025-02-21": "47882",
        "2025-02-22": "48192",
        "2025-02-23": "48318",
        "2025-02-24": "48491",
        "2025-02-25": "48780",
        "2025-02-26": "49137"
    },
    "topDestinationHosts": {
        "Pressable": 8296,
        "Bluehost": 3765,
        "Kinsta": 3059,
        "Digital Ocean": 3003,
        "SiteGround": 2678,
        "Hostinger": 1703,
        "GoDaddy": 835,
        "BigScoots": 399,
        "Liquid Web": 304,
        "Elementor Hosting": 257,
        "GridPane": 245,
        "WordPress.com": 220,
        "InMotion Hosting": 208,
        "OVH": 191,
        "IONOS": 183,
        "A2 Hosting": 160,
        "Wordify": 158,
        "Namecheap": 151,
        "DreamHost": 149,
        "Hetzner Online": 136
    },
    "dailyTotalStat": {
        "2024-09-21": "745273",
        "2024-09-22": "744978",
        "2024-09-23": "744642",
        "2024-09-24": "744305",
        "2024-09-25": "743898",
        "2024-09-26": "743497",
        "2024-09-27": "743076",
        "2024-09-28": "742659",
        "2024-09-29": "742266",
        "2024-09-30": "741849",
        "2024-10-01": "741437",
        "2024-10-02": "741030",
        "2024-10-03": "740543",
        "2024-10-04": "740090",
        "2024-10-05": "739667",
        "2024-10-06": "739341",
        "2024-10-07": "739102",
        "2024-10-08": "738901",
        "2024-10-09": "736803",
        "2024-10-10": "735829",
        "2024-10-11": "735997",
        "2024-10-12": "735841",
        "2024-10-13": "735365",
        "2024-10-14": "734798",
        "2024-10-15": "734234",
        "2024-10-16": "733668",
        "2024-10-17": "733075",
        "2024-10-18": "732477",
        "2024-10-19": "731732",
        "2024-10-20": "731533",
        "2024-10-21": "731196",
        "2024-10-22": "730633",
        "2024-10-23": "729850",
        "2024-10-24": "729189",
        "2024-10-25": "728350",
        "2024-10-26": "727792",
        "2024-10-27": "727537",
        "2024-10-28": "727127",
        "2024-10-29": "726413",
        "2024-10-30": "725658",
        "2024-10-31": "725027",
        "2024-11-01": "724384",
        "2024-11-02": "723748",
        "2024-11-03": "723544",
        "2024-11-04": "723276",
        "2024-11-05": "722762",
        "2024-11-06": "721646",
        "2024-11-07": "721100",
        "2024-11-08": "720563",
        "2024-11-09": "720107",
        "2024-11-10": "719748",
        "2024-11-11": "719157",
        "2024-11-12": "718533",
        "2024-11-13": "718108",
        "2024-11-14": "717543",
        "2024-11-15": "716862",
        "2024-11-16": "716381",
        "2024-11-17": "716544",
        "2024-11-18": "715924",
        "2024-11-19": "715530",
        "2024-11-20": "714747",
        "2024-11-21": "712869",
        "2024-11-22": "712189",
        "2024-11-23": "711241",
        "2024-11-24": "707360",
        "2024-11-25": "707035",
        "2024-11-26": "705867",
        "2024-11-27": "704968",
        "2024-11-28": "704773",
        "2024-11-29": "704054",
        "2024-11-30": "703389",
        "2024-12-01": "704036",
        "2024-12-02": "702375",
        "2024-12-03": "701792",
        "2024-12-04": "701042",
        "2024-12-05": "696740",
        "2024-12-06": "698884",
        "2024-12-07": "698514",
        "2024-12-08": "699485",
        "2024-12-09": "698652",
        "2024-12-10": "697735",
        "2024-12-11": "696939",
        "2024-12-12": "696102",
        "2024-12-13": "695379",
        "2024-12-14": "695120",
        "2024-12-15": "695355",
        "2024-12-16": "694609",
        "2024-12-17": "693450",
        "2024-12-18": "692442",
        "2024-12-19": "691658",
        "2024-12-20": "690920",
        "2024-12-21": "690540",
        "2024-12-22": "691624",
        "2024-12-23": "691068",
        "2024-12-24": "690561",
        "2024-12-25": "690090",
        "2024-12-26": "689848",
        "2024-12-27": "689507",
        "2024-12-28": "689283",
        "2024-12-29": "689259",
        "2024-12-30": "689405",
        "2024-12-31": "688931",
        "2025-01-01": "687715",
        "2025-01-02": "687730",
        "2025-01-03": "687184",
        "2025-01-04": "686846",
        "2025-01-05": "687164",
        "2025-01-06": "686406",
        "2025-01-07": "685764",
        "2025-01-08": "685098",
        "2025-01-09": "684352",
        "2025-01-10": "683649",
        "2025-01-11": "683469",
        "2025-01-12": "683870",
        "2025-01-13": "683311",
        "2025-01-14": "681951",
        "2025-01-15": "681361",
        "2025-01-16": "679845",
        "2025-01-17": "680011",
        "2025-01-18": "679707",
        "2025-01-19": "679384",
        "2025-01-20": "678744",
        "2025-01-21": "677599",
        "2025-01-22": "677146",
        "2025-01-23": "676540",
        "2025-01-24": "675709",
        "2025-01-25": "675206",
        "2025-01-26": "676118",
        "2025-01-27": "675609",
        "2025-01-28": "674792",
        "2025-01-29": "673810",
        "2025-01-30": "672846",
        "2025-01-31": "672312",
        "2025-02-01": "671790",
        "2025-02-02": "672254",
        "2025-02-03": "671412",
        "2025-02-04": "671037",
        "2025-02-05": "670202",
        "2025-02-06": "669214",
        "2025-02-07": "668683",
        "2025-02-08": "668510",
        "2025-02-09": "668561",
        "2025-02-10": "668007",
        "2025-02-11": "667450",
        "2025-02-12": "666532",
        "2025-02-13": "666044",
        "2025-02-14": "665532",
        "2025-02-15": "665153",
        "2025-02-16": "665560",
        "2025-02-17": "664940",
        "2025-02-18": "664135",
        "2025-02-19": "663612",
        "2025-02-20": "662785",
        "2025-02-21": "662256",
        "2025-02-22": "661935",
        "2025-02-23": "662446",
        "2025-02-24": "661965",
        "2025-02-25": "661139",
        "2025-02-26": "660657"
    }
}